geviewer/__init__.py
geviewer/converter.py
geviewer/geometry.py
geviewer/geviewer.py
geviewer/gui.py
geviewer/parsers.py
geviewer/utils.py
geviewer/viewer.py
geviewer-0.2.1.dist-info/LICENSE
geviewer-0.2.1.dist-info/METADATA
geviewer-0.2.1.dist-info/WHEEL
geviewer-0.2.1.dist-info/entry_points.txt
geviewer-0.2.1.dist-info/top_level.txt
geviewer-0.2.1.dist-info/RECORD
