Metadata-Version: 2.1
Name: geviewer
Version: 0.2.1
Summary: A lightweight, Python-based visualization tool for Geant4.
Home-page: https://github.com/clarkehardy/geviewer.git
Author: Clarke Hardy
Author-email: Clarke Hardy <cahardy@stanford.edu>
License: MIT
Project-URL: repository, https://github.com/clarkehardy/geviewer.git
Project-URL: documentation, https://geviewer.readthedocs.io/
Keywords: geant4,viewer,visualizer,display,event,simulation,hep,physics,particle,track,detector,geometry,vrml,heprep
Requires-Python: >=3.8
License-File: LICENSE
Requires-Dist: PyQt6
Requires-Dist: pyvistaqt
Requires-Dist: lxml
Requires-Dist: tqdm
